bany/__init__.py
bany/__main__.py
bany/cmd/__init__.py
bany/cmd/extract/__init__.py
bany/cmd/extract/app.py
bany/cmd/extract/rules.py
bany/cmd/extract/extractors/__init__.py
bany/cmd/extract/extractors/base.py
bany/cmd/extract/extractors/pdf.py
bany/cmd/solve/__init__.py
bany/cmd/solve/app.py
bany/cmd/solve/network/__init__.py
bany/cmd/solve/network/algo.py
bany/cmd/solve/network/attrs.py
bany/cmd/solve/network/loader.py
bany/cmd/solve/network/validate.py
bany/cmd/solve/network/visualize.py
bany/cmd/solve/solvers/__init__.py
bany/cmd/solve/solvers/basesolver.py
bany/cmd/solve/solvers/bucketdata.py
bany/cmd/solve/solvers/constrained.py
bany/cmd/solve/solvers/graphsolver.py
bany/cmd/solve/solvers/montecarlo.py
bany/cmd/solve/solvers/unconstrained.py
bany/cmd/split/__init__.py
bany/cmd/split/app.py
bany/cmd/split/splitter.py
bany/cmd/ynab/__init__.py
bany/cmd/ynab/app.py
bany/core/__init__.py
bany/core/cache.py
bany/core/config.py
bany/core/logger.py
bany/core/money.py
bany/core/settings.py
bany/ynab/__init__.py
bany/ynab/api.py
bany/ynab/mock.py
bany/ynab/transaction.py
bany-2.0.1.dist-info/METADATA
bany-2.0.1.dist-info/WHEEL
bany-2.0.1.dist-info/entry_points.txt
bany-2.0.1.dist-info/licenses/LICENSE
bany-2.0.1.dist-info/RECORD
