Metadata-Version: 2.4
Name: bany
Version: 2.0.1
Summary: A collection of scripts for personal finance
Project-URL: Repository, https://github.com/AdamGagorik/bany
Author-email: Adam Gagorik <adam.gagorik@gmail.com>
License:            DO WHAT THE FUCK YOU WANT TO PUBLIC LICENSE
License-File: LICENSE
Requires-Python: >=3.13.0
Requires-Dist: cmd2>=2.5.11
Requires-Dist: diskcache>=5.6.3
Requires-Dist: networkx>=3.4.2
Requires-Dist: numpy>=2.2.4
Requires-Dist: oauthlib>=3.2.2
Requires-Dist: openpyxl>=3.1.5
Requires-Dist: pandas>=2.2.3
Requires-Dist: pdfplumber>=0.11.6
Requires-Dist: py-moneyed>=3.0
Requires-Dist: pydantic-settings>=2.8.1
Requires-Dist: pydantic>=2.11.3
Requires-Dist: python-dateutil>=2.9.0.post0
Requires-Dist: python-dotenv>=1.1.0
Requires-Dist: pyyaml>=6.0.2
Requires-Dist: requests>=2.32.3
Requires-Dist: responses>=0.25.7
Requires-Dist: rich>=14.0.0
Requires-Dist: scipy>=1.15.2
Requires-Dist: textualize>=0.1
Requires-Dist: typer>=0.15.2
